{"cameraMode":{"drawMode":0,"name":"Shaded","section":"Shading Mode"},"sceneLighting":true,"audioPlay":false,"sceneViewState":{"m_AlwaysRefresh":false,"showFog":true,"showSkybox":true,"showFlares":true,"showImageEffects":true,"showParticleSystems":true,"showVisualEffectGraphs":true,"m_FxEnabled":true},"in2DMode":false,"pivot":{"x":-6.0722575187683109,"y":-6.834430694580078,"z":13.35472297668457},"rotation":{"x":-0.23915992677211762,"y":0.25894591212272646,"z":-0.06634204089641571,"w":-0.9334717988967896},"size":11.6436128616333,"orthographic":false}